odoo/addons/purchase_order_supplierinfo_update/README.rst
odoo/addons/purchase_order_supplierinfo_update/__init__.py
odoo/addons/purchase_order_supplierinfo_update/__manifest__.py
odoo/addons/purchase_order_supplierinfo_update/i18n/it.po
odoo/addons/purchase_order_supplierinfo_update/i18n/pt_BR.po
odoo/addons/purchase_order_supplierinfo_update/i18n/purchase_order_supplierinfo_update.pot
odoo/addons/purchase_order_supplierinfo_update/models/__init__.py
odoo/addons/purchase_order_supplierinfo_update/models/purchase_order.py
odoo/addons/purchase_order_supplierinfo_update/readme/CONTRIBUTORS.md
odoo/addons/purchase_order_supplierinfo_update/readme/DESCRIPTION.md
odoo/addons/purchase_order_supplierinfo_update/readme/ROADMAP.md
odoo/addons/purchase_order_supplierinfo_update/readme/USAGE.md
odoo/addons/purchase_order_supplierinfo_update/static/description/icon.png
odoo/addons/purchase_order_supplierinfo_update/static/description/index.html
odoo/addons/purchase_order_supplierinfo_update/tests/__init__.py
odoo/addons/purchase_order_supplierinfo_update/tests/test_purchase_order_supplierinfo_update.py
odoo_addon_purchase_order_supplierinfo_update-18.0.1.0.1.dist-info/METADATA
odoo_addon_purchase_order_supplierinfo_update-18.0.1.0.1.dist-info/WHEEL
odoo_addon_purchase_order_supplierinfo_update-18.0.1.0.1.dist-info/top_level.txt
odoo_addon_purchase_order_supplierinfo_update-18.0.1.0.1.dist-info/RECORD
